odoo/addons/ir_filters_multi_company/README.rst
odoo/addons/ir_filters_multi_company/__init__.py
odoo/addons/ir_filters_multi_company/__manifest__.py
odoo/addons/ir_filters_multi_company/hooks/post_init_hook.py
odoo/addons/ir_filters_multi_company/i18n/ir_filters_multi_company.pot
odoo/addons/ir_filters_multi_company/models/__init__.py
odoo/addons/ir_filters_multi_company/models/ir_filters.py
odoo/addons/ir_filters_multi_company/readme/CONTRIBUTORS.rst
odoo/addons/ir_filters_multi_company/readme/DESCRIPTION.rst
odoo/addons/ir_filters_multi_company/security/ir_filters.xml
odoo/addons/ir_filters_multi_company/static/description/icon.png
odoo/addons/ir_filters_multi_company/static/description/index.html
odoo/addons/ir_filters_multi_company/views/ir_filters.xml
odoo12_addon_ir_filters_multi_company-12.0.1.0.0.99.dev4.dist-info/METADATA
odoo12_addon_ir_filters_multi_company-12.0.1.0.0.99.dev4.dist-info/WHEEL
odoo12_addon_ir_filters_multi_company-12.0.1.0.0.99.dev4.dist-info/top_level.txt
odoo12_addon_ir_filters_multi_company-12.0.1.0.0.99.dev4.dist-info/RECORD
